indomath/__init__.py
indomath/geometry.py
indomath/matrix.py
indomath/mtk.py
indomath-0.3.6.dist-info/METADATA
indomath-0.3.6.dist-info/WHEEL
indomath-0.3.6.dist-info/top_level.txt
indomath-0.3.6.dist-info/RECORD
