Metadata-Version: 2.1
Name: indomath
Version: 0.3.6
Summary: Sebuah progam matematika
Author: VincentVe,Febrianto
Author-email: sayuzvernando1@gmail.com
License: MIT
